gboml/__init__.py
gboml/gboml_graph.py
gboml/gboml_main.py
gboml/version.py
gboml/compiler/__init__.py
gboml/compiler/gboml_compiler.py
gboml/compiler/gboml_lexer.py
gboml/compiler/gboml_matrix_generation.py
gboml/compiler/gboml_parser.py
gboml/compiler/gboml_semantic.py
gboml/compiler/utils.py
gboml/compiler/classes/__init__.py
gboml/compiler/classes/condition.py
gboml/compiler/classes/constraint.py
gboml/compiler/classes/error.py
gboml/compiler/classes/expression.py
gboml/compiler/classes/factor.py
gboml/compiler/classes/identifier.py
gboml/compiler/classes/limited_size_dict.py
gboml/compiler/classes/link.py
gboml/compiler/classes/mdp.py
gboml/compiler/classes/node.py
gboml/compiler/classes/objective.py
gboml/compiler/classes/parameter.py
gboml/compiler/classes/parent.py
gboml/compiler/classes/program.py
gboml/compiler/classes/time_obj.py
gboml/compiler/classes/variable.py
gboml/compiler/ply/__init__.py
gboml/compiler/ply/lex.py
gboml/compiler/ply/yacc.py
gboml/output/__init__.py
gboml/output/gboml_output.py
gboml/solver_api/__init__.py
gboml/solver_api/cbc_solver.py
gboml/solver_api/clp_solver.py
gboml/solver_api/cplex.opt
gboml/solver_api/cplex_solver.py
gboml/solver_api/dsp_solver.py
gboml/solver_api/dsppy.py
gboml/solver_api/gurobi.opt
gboml/solver_api/gurobi_solver.py
gboml/solver_api/highs.opt
gboml/solver_api/highs_solver.py
gboml/solver_api/pycbc.py
gboml/solver_api/pyhighs.py
gboml/solver_api/scipy_solver.py
gboml/solver_api/xpress.opt
gboml/solver_api/xpress_solver.py
gboml-0.1.10.dist-info/AUTHORS
gboml-0.1.10.dist-info/LICENSE.txt
gboml-0.1.10.dist-info/METADATA
gboml-0.1.10.dist-info/WHEEL
gboml-0.1.10.dist-info/entry_points.txt
gboml-0.1.10.dist-info/top_level.txt
gboml-0.1.10.dist-info/RECORD
