Metadata-Version: 2.1
Name: gboml
Version: 0.1.10
Summary: GBOML: Graph-Based Optimization Modeling Language
Home-page: https://gitlab.uliege.be/smart_grids/public/gboml
Author: Bardhyl Miftari, Mathias Berger, Hatim Djelassi, Damien Ernst
Author-email: bmiftari@uliege.be
Classifier: Development Status :: 1 - Planning
Classifier: Intended Audience :: Science/Research
Classifier: Operating System :: POSIX :: Linux
Classifier: Operating System :: Microsoft :: Windows
Classifier: Operating System :: MacOS
Classifier: Programming Language :: Python :: 3.7
Classifier: Programming Language :: Python :: 3.8
Classifier: Programming Language :: Python :: 3.9
Classifier: Topic :: Scientific/Engineering
Classifier: Topic :: Scientific/Engineering :: Mathematics
Classifier: Topic :: Software Development :: Compilers
Requires-Python: >=3.7
License-File: LICENSE.txt
License-File: AUTHORS
Requires-Dist: numpy>=1.19.4
Requires-Dist: scipy>=1.5.3
Provides-Extra: all_solvers
Requires-Dist: cplex; extra == "all-solvers"
Requires-Dist: cylp; extra == "all-solvers"
Requires-Dist: xpress; extra == "all-solvers"
Requires-Dist: gurobipy; extra == "all-solvers"
Provides-Extra: cbc
Requires-Dist: cylp; extra == "cbc"
Provides-Extra: cplex
Requires-Dist: cplex; extra == "cplex"
Provides-Extra: gurobi
Requires-Dist: gurobipy; extra == "gurobi"
Provides-Extra: xpress
Requires-Dist: xpress; extra == "xpress"
